sanskritutf/__init__.py
sanskritutf/sanskritutf.py
tests/__init__.py
tests/test_sanskritutf.py
sanskritutf-1.0.0.dist-info/METADATA
sanskritutf-1.0.0.dist-info/WHEEL
sanskritutf-1.0.0.dist-info/top_level.txt
sanskritutf-1.0.0.dist-info/RECORD
