Metadata-Version: 2.1
Name: sanskritutf
Version: 1.0.0
Summary: Sanskrit to Utf converter
Author: Ashok Kumar
Author-email: agi <agi9feb99@gmail.com>
Project-URL: Homepage, https://github.com/agi9feb99/sanskritutf
Keywords: sanskrit,utf,dictionary
Classifier: License :: OSI Approved :: MIT License
Classifier: Programming Language :: Python
Classifier: Programming Language :: Python :: 3
Requires-Python: >=3.7
Requires-Dist: tomli ; python_version < "3.11"
Provides-Extra: dev
Requires-Dist: pytest ; extra == 'dev'
